[{"trends":[{"name":"Michigan","url":"http:\/\/twitter.com\/search?q=Michigan","promoted_content":null,"query":"Michigan","tweet_volume":286564},{"name":"Harbaugh","url":"http:\/\/twitter.com\/search?q=Harbaugh","promoted_content":null,"query":"Harbaugh","tweet_volume":20126},{"name":"#DeactivateTrump","url":"http:\/\/twitter.com\/search?q=%23DeactivateTrump","promoted_content":null,"query":"%23DeactivateTrump","tweet_volume":40494},{"name":"#TurkishGP","url":"http:\/\/twitter.com\/search?q=%23TurkishGP","promoted_content":null,"query":"%23TurkishGP","tweet_volume":272136},{"name":"Lewis Hamilton","url":"http:\/\/twitter.com\/search?q=%22Lewis+Hamilton%22","promoted_content":null,"query":"%22Lewis+Hamilton%22","tweet_volume":52911},{"name":"Vettel","url":"http:\/\/twitter.com\/search?q=Vettel","promoted_content":null,"query":"Vettel","tweet_volume":73998},{"name":"#SundayMorning","url":"http:\/\/twitter.com\/search?q=%23SundayMorning","promoted_content":null,"query":"%23SundayMorning","tweet_volume":null},{"name":"#TurkeyGP","url":"http:\/\/twitter.com\/search?q=%23TurkeyGP","promoted_content":null,"query":"%23TurkeyGP","tweet_volume":13649},{"name":"#sundayvibes","url":"http:\/\/twitter.com\/search?q=%23sundayvibes","promoted_content":null,"query":"%23sundayvibes","tweet_volume":18893},{"name":"Antifa","url":"http:\/\/twitter.com\/search?q=Antifa","promoted_content":null,"query":"Antifa","tweet_volume":1157552},{"name":"Jeezy","url":"http:\/\/twitter.com\/search?q=Jeezy","promoted_content":null,"query":"Jeezy","tweet_volume":50551},{"name":"Bottas","url":"http:\/\/twitter.com\/search?q=Bottas","promoted_content":null,"query":"Bottas","tweet_volume":22789},{"name":"SHINee","url":"http:\/\/twitter.com\/search?q=SHINee","promoted_content":null,"query":"SHINee","tweet_volume":360732},{"name":"Good Sunday","url":"http:\/\/twitter.com\/search?q=%22Good+Sunday%22","promoted_content":null,"query":"%22Good+Sunday%22","tweet_volume":36577},{"name":"Proud Boys","url":"http:\/\/twitter.com\/search?q=%22Proud+Boys%22","promoted_content":null,"query":"%22Proud+Boys%22","tweet_volume":343430},{"name":"Albon","url":"http:\/\/twitter.com\/search?q=Albon","promoted_content":null,"query":"Albon","tweet_volume":20118},{"name":"megan","url":"http:\/\/twitter.com\/search?q=megan","promoted_content":null,"query":"megan","tweet_volume":36837},{"name":"Checo","url":"http:\/\/twitter.com\/search?q=Checo","promoted_content":null,"query":"Checo","tweet_volume":16629},{"name":"Crawford","url":"http:\/\/twitter.com\/search?q=Crawford","promoted_content":null,"query":"Crawford","tweet_volume":62188},{"name":"Verstappen","url":"http:\/\/twitter.com\/search?q=Verstappen","promoted_content":null,"query":"Verstappen","tweet_volume":37583},{"name":"Perez","url":"http:\/\/twitter.com\/search?q=Perez","promoted_content":null,"query":"Perez","tweet_volume":80026},{"name":"World Champion","url":"http:\/\/twitter.com\/search?q=%22World+Champion%22","promoted_content":null,"query":"%22World+Champion%22","tweet_volume":34807},{"name":"Jodi","url":"http:\/\/twitter.com\/search?q=Jodi","promoted_content":null,"query":"Jodi","tweet_volume":null},{"name":"Spence","url":"http:\/\/twitter.com\/search?q=Spence","promoted_content":null,"query":"Spence","tweet_volume":13078},{"name":"SBMM","url":"http:\/\/twitter.com\/search?q=SBMM","promoted_content":null,"query":"SBMM","tweet_volume":null},{"name":"Stroll","url":"http:\/\/twitter.com\/search?q=Stroll","promoted_content":null,"query":"Stroll","tweet_volume":99806},{"name":"Ferrari","url":"http:\/\/twitter.com\/search?q=Ferrari","promoted_content":null,"query":"Ferrari","tweet_volume":37217},{"name":"Andy Ngo","url":"http:\/\/twitter.com\/search?q=%22Andy+Ngo%22","promoted_content":null,"query":"%22Andy+Ngo%22","tweet_volume":null},{"name":"Racing Point","url":"http:\/\/twitter.com\/search?q=%22Racing+Point%22","promoted_content":null,"query":"%22Racing+Point%22","tweet_volume":12895},{"name":"anita","url":"http:\/\/twitter.com\/search?q=anita","promoted_content":null,"query":"anita","tweet_volume":19443},{"name":"minho","url":"http:\/\/twitter.com\/search?q=minho","promoted_content":null,"query":"minho","tweet_volume":345201},{"name":"oregon state","url":"http:\/\/twitter.com\/search?q=%22oregon+state%22","promoted_content":null,"query":"%22oregon+state%22","tweet_volume":null},{"name":"KIM LIP","url":"http:\/\/twitter.com\/search?q=%22KIM+LIP%22","promoted_content":null,"query":"%22KIM+LIP%22","tweet_volume":null},{"name":"DACA","url":"http:\/\/twitter.com\/search?q=DACA","promoted_content":null,"query":"DACA","tweet_volume":66412},{"name":"beavs","url":"http:\/\/twitter.com\/search?q=beavs","promoted_content":null,"query":"beavs","tweet_volume":null},{"name":"Dongwoo","url":"http:\/\/twitter.com\/search?q=Dongwoo","promoted_content":null,"query":"Dongwoo","tweet_volume":21986},{"name":"beavers","url":"http:\/\/twitter.com\/search?q=beavers","promoted_content":null,"query":"beavers","tweet_volume":null},{"name":"shrek","url":"http:\/\/twitter.com\/search?q=shrek","promoted_content":null,"query":"shrek","tweet_volume":19858},{"name":"Pac 12","url":"http:\/\/twitter.com\/search?q=%22Pac+12%22","promoted_content":null,"query":"%22Pac+12%22","tweet_volume":null},{"name":"Bob Arum","url":"http:\/\/twitter.com\/search?q=%22Bob+Arum%22","promoted_content":null,"query":"%22Bob+Arum%22","tweet_volume":null},{"name":"Inkigayo","url":"http:\/\/twitter.com\/search?q=Inkigayo","promoted_content":null,"query":"Inkigayo","tweet_volume":77420},{"name":"huskies","url":"http:\/\/twitter.com\/search?q=huskies","promoted_content":null,"query":"huskies","tweet_volume":null},{"name":"doors","url":"http:\/\/twitter.com\/search?q=doors","promoted_content":null,"query":"doors","tweet_volume":36341},{"name":"Canelo","url":"http:\/\/twitter.com\/search?q=Canelo","promoted_content":null,"query":"Canelo","tweet_volume":null},{"name":"Chaka Khan","url":"http:\/\/twitter.com\/search?q=%22Chaka+Khan%22","promoted_content":null,"query":"%22Chaka+Khan%22","tweet_volume":null},{"name":"kyungsoo","url":"http:\/\/twitter.com\/search?q=kyungsoo","promoted_content":null,"query":"kyungsoo","tweet_volume":88217},{"name":"Cara Dune","url":"http:\/\/twitter.com\/search?q=%22Cara+Dune%22","promoted_content":null,"query":"%22Cara+Dune%22","tweet_volume":null},{"name":"Maloney","url":"http:\/\/twitter.com\/search?q=Maloney","promoted_content":null,"query":"Maloney","tweet_volume":null},{"name":"Lane Kiffin","url":"http:\/\/twitter.com\/search?q=%22Lane+Kiffin%22","promoted_content":null,"query":"%22Lane+Kiffin%22","tweet_volume":null},{"name":"Trumps America","url":"http:\/\/twitter.com\/search?q=%22Trumps+America%22","promoted_content":null,"query":"%22Trumps+America%22","tweet_volume":null}],"as_of":"2020-11-15T12:30:59Z","created_at":"2020-11-13T11:49:43Z","locations":[{"name":"Columbus","woeid":2383660}]}]