[{"trends":[{"name":"New Philadelphia","url":"http:\/\/twitter.com\/search?q=%22New+Philadelphia%22","promoted_content":null,"query":"%22New+Philadelphia%22","tweet_volume":10502},{"name":"Walmart","url":"http:\/\/twitter.com\/search?q=Walmart","promoted_content":null,"query":"Walmart","tweet_volume":109891},{"name":"billie","url":"http:\/\/twitter.com\/search?q=billie","promoted_content":null,"query":"billie","tweet_volume":133368},{"name":"The Weeknd","url":"http:\/\/twitter.com\/search?q=%22The+Weeknd%22","promoted_content":null,"query":"%22The+Weeknd%22","tweet_volume":37558},{"name":"Golden Goose","url":"http:\/\/twitter.com\/search?q=%22Golden+Goose%22","promoted_content":null,"query":"%22Golden+Goose%22","tweet_volume":56415},{"name":"#PS5Launch","url":"http:\/\/twitter.com\/search?q=%23PS5Launch","promoted_content":null,"query":"%23PS5Launch","tweet_volume":null},{"name":"Cold War","url":"http:\/\/twitter.com\/search?q=%22Cold+War%22","promoted_content":null,"query":"%22Cold+War%22","tweet_volume":52536},{"name":"#ThursdayThoughts","url":"http:\/\/twitter.com\/search?q=%23ThursdayThoughts","promoted_content":null,"query":"%23ThursdayThoughts","tweet_volume":47438},{"name":"#PlayStation5","url":"http:\/\/twitter.com\/search?q=%23PlayStation5","promoted_content":null,"query":"%23PlayStation5","tweet_volume":73251},{"name":"Puerto Rico","url":"http:\/\/twitter.com\/search?q=%22Puerto+Rico%22","promoted_content":null,"query":"%22Puerto+Rico%22","tweet_volume":22759},{"name":"Dominion","url":"http:\/\/twitter.com\/search?q=Dominion","promoted_content":null,"query":"Dominion","tweet_volume":763590},{"name":"Friday the 13th","url":"http:\/\/twitter.com\/search?q=%22Friday+the+13th%22","promoted_content":null,"query":"%22Friday+the+13th%22","tweet_volume":51244},{"name":"#WearAMask","url":"http:\/\/twitter.com\/search?q=%23WearAMask","promoted_content":null,"query":"%23WearAMask","tweet_volume":13326},{"name":"Lakers","url":"http:\/\/twitter.com\/search?q=Lakers","promoted_content":null,"query":"Lakers","tweet_volume":36700},{"name":"Miles Morales","url":"http:\/\/twitter.com\/search?q=%22Miles+Morales%22","promoted_content":null,"query":"%22Miles+Morales%22","tweet_volume":37683},{"name":"Westbrook","url":"http:\/\/twitter.com\/search?q=Westbrook","promoted_content":null,"query":"Westbrook","tweet_volume":87463},{"name":"Knicks","url":"http:\/\/twitter.com\/search?q=Knicks","promoted_content":null,"query":"Knicks","tweet_volume":27824},{"name":"Sheetz","url":"http:\/\/twitter.com\/search?q=Sheetz","promoted_content":null,"query":"Sheetz","tweet_volume":null},{"name":"Dearra","url":"http:\/\/twitter.com\/search?q=Dearra","promoted_content":null,"query":"Dearra","tweet_volume":null},{"name":"Demar","url":"http:\/\/twitter.com\/search?q=Demar","promoted_content":null,"query":"Demar","tweet_volume":null},{"name":"DeRozan","url":"http:\/\/twitter.com\/search?q=DeRozan","promoted_content":null,"query":"DeRozan","tweet_volume":null},{"name":"#themasters","url":"http:\/\/twitter.com\/search?q=%23themasters","promoted_content":null,"query":"%23themasters","tweet_volume":44841},{"name":"Corey Lewandowski","url":"http:\/\/twitter.com\/search?q=%22Corey+Lewandowski%22","promoted_content":null,"query":"%22Corey+Lewandowski%22","tweet_volume":23479},{"name":"Danny Green","url":"http:\/\/twitter.com\/search?q=%22Danny+Green%22","promoted_content":null,"query":"%22Danny+Green%22","tweet_volume":null},{"name":"Kemba","url":"http:\/\/twitter.com\/search?q=Kemba","promoted_content":null,"query":"Kemba","tweet_volume":null},{"name":"Rewind","url":"http:\/\/twitter.com\/search?q=Rewind","promoted_content":null,"query":"Rewind","tweet_volume":31273},{"name":"Lletget","url":"http:\/\/twitter.com\/search?q=Lletget","promoted_content":null,"query":"Lletget","tweet_volume":null},{"name":"OANN","url":"http:\/\/twitter.com\/search?q=OANN","promoted_content":null,"query":"OANN","tweet_volume":408815},{"name":"Big Sur","url":"http:\/\/twitter.com\/search?q=%22Big+Sur%22","promoted_content":null,"query":"%22Big+Sur%22","tweet_volume":10504},{"name":"Doctors Without Borders","url":"http:\/\/twitter.com\/search?q=%22Doctors+Without+Borders%22","promoted_content":null,"query":"%22Doctors+Without+Borders%22","tweet_volume":25746},{"name":"Oladipo","url":"http:\/\/twitter.com\/search?q=Oladipo","promoted_content":null,"query":"Oladipo","tweet_volume":null},{"name":"Chachi","url":"http:\/\/twitter.com\/search?q=Chachi","promoted_content":null,"query":"Chachi","tweet_volume":null},{"name":"Tiger Woods","url":"http:\/\/twitter.com\/search?q=%22Tiger+Woods%22","promoted_content":null,"query":"%22Tiger+Woods%22","tweet_volume":null},{"name":"Paul Casey","url":"http:\/\/twitter.com\/search?q=%22Paul+Casey%22","promoted_content":null,"query":"%22Paul+Casey%22","tweet_volume":null},{"name":"Spurs","url":"http:\/\/twitter.com\/search?q=Spurs","promoted_content":null,"query":"Spurs","tweet_volume":27460},{"name":"Supreme Courtyard Marriott","url":"http:\/\/twitter.com\/search?q=%22Supreme+Courtyard+Marriott%22","promoted_content":null,"query":"%22Supreme+Courtyard+Marriott%22","tweet_volume":null},{"name":"Deutsche Bank","url":"http:\/\/twitter.com\/search?q=%22Deutsche+Bank%22","promoted_content":null,"query":"%22Deutsche+Bank%22","tweet_volume":16939},{"name":"Musah","url":"http:\/\/twitter.com\/search?q=Musah","promoted_content":null,"query":"Musah","tweet_volume":null},{"name":"DMCA","url":"http:\/\/twitter.com\/search?q=DMCA","promoted_content":null,"query":"DMCA","tweet_volume":19289},{"name":"The PS5","url":"http:\/\/twitter.com\/search?q=%22The+PS5%22","promoted_content":null,"query":"%22The+PS5%22","tweet_volume":225296},{"name":"Staten Island","url":"http:\/\/twitter.com\/search?q=%22Staten+Island%22","promoted_content":null,"query":"%22Staten+Island%22","tweet_volume":13470},{"name":"Abel","url":"http:\/\/twitter.com\/search?q=Abel","promoted_content":null,"query":"Abel","tweet_volume":53813},{"name":"Scott Baio","url":"http:\/\/twitter.com\/search?q=%22Scott+Baio%22","promoted_content":null,"query":"%22Scott+Baio%22","tweet_volume":null},{"name":"Happy Founders","url":"http:\/\/twitter.com\/search?q=%22Happy+Founders%22","promoted_content":null,"query":"%22Happy+Founders%22","tweet_volume":null},{"name":"Pope Francis","url":"http:\/\/twitter.com\/search?q=%22Pope+Francis%22","promoted_content":null,"query":"%22Pope+Francis%22","tweet_volume":18943},{"name":"Jurassic Park","url":"http:\/\/twitter.com\/search?q=%22Jurassic+Park%22","promoted_content":null,"query":"%22Jurassic+Park%22","tweet_volume":12990},{"name":"Cleo","url":"http:\/\/twitter.com\/search?q=Cleo","promoted_content":null,"query":"Cleo","tweet_volume":10719},{"name":"Hornets","url":"http:\/\/twitter.com\/search?q=Hornets","promoted_content":null,"query":"Hornets","tweet_volume":16007},{"name":"Not Ken","url":"http:\/\/twitter.com\/search?q=%22Not+Ken%22","promoted_content":null,"query":"%22Not+Ken%22","tweet_volume":null},{"name":"Kroos","url":"http:\/\/twitter.com\/search?q=Kroos","promoted_content":null,"query":"Kroos","tweet_volume":41243}],"as_of":"2020-11-12T19:48:12Z","created_at":"2020-11-11T05:03:08Z","locations":[{"name":"Philadelphia","woeid":2471217}]}]