[{"trends":[{"name":"#RHOSLC","url":"http:\/\/twitter.com\/search?q=%23RHOSLC","promoted_content":null,"query":"%23RHOSLC","tweet_volume":18847},{"name":"#YouTubeDOWN","url":"http:\/\/twitter.com\/search?q=%23YouTubeDOWN","promoted_content":null,"query":"%23YouTubeDOWN","tweet_volume":249942},{"name":"Russ","url":"http:\/\/twitter.com\/search?q=Russ","promoted_content":null,"query":"Russ","tweet_volume":36182},{"name":"Chris Brown","url":"http:\/\/twitter.com\/search?q=%22Chris+Brown%22","promoted_content":null,"query":"%22Chris+Brown%22","tweet_volume":20206},{"name":"#CMAawards","url":"http:\/\/twitter.com\/search?q=%23CMAawards","promoted_content":null,"query":"%23CMAawards","tweet_volume":44174},{"name":"Westbrook","url":"http:\/\/twitter.com\/search?q=Westbrook","promoted_content":null,"query":"Westbrook","tweet_volume":64017},{"name":"#TGTATBO","url":"http:\/\/twitter.com\/search?q=%23TGTATBO","promoted_content":null,"query":"%23TGTATBO","tweet_volume":16113},{"name":"The Rockets","url":"http:\/\/twitter.com\/search?q=%22The+Rockets%22","promoted_content":null,"query":"%22The+Rockets%22","tweet_volume":33751},{"name":"#MACtion","url":"http:\/\/twitter.com\/search?q=%23MACtion","promoted_content":null,"query":"%23MACtion","tweet_volume":null},{"name":"Nestor","url":"http:\/\/twitter.com\/search?q=Nestor","promoted_content":null,"query":"Nestor","tweet_volume":26178},{"name":"minghao","url":"http:\/\/twitter.com\/search?q=minghao","promoted_content":null,"query":"minghao","tweet_volume":26215},{"name":"Karl Rove","url":"http:\/\/twitter.com\/search?q=%22Karl+Rove%22","promoted_content":null,"query":"%22Karl+Rove%22","tweet_volume":20783},{"name":"Charley Pride","url":"http:\/\/twitter.com\/search?q=%22Charley+Pride%22","promoted_content":null,"query":"%22Charley+Pride%22","tweet_volume":null},{"name":"GameStop","url":"http:\/\/twitter.com\/search?q=GameStop","promoted_content":null,"query":"GameStop","tweet_volume":17381},{"name":"Eric Church","url":"http:\/\/twitter.com\/search?q=%22Eric+Church%22","promoted_content":null,"query":"%22Eric+Church%22","tweet_volume":null},{"name":"Hawks","url":"http:\/\/twitter.com\/search?q=Hawks","promoted_content":null,"query":"Hawks","tweet_volume":33064},{"name":"mark lee","url":"http:\/\/twitter.com\/search?q=%22mark+lee%22","promoted_content":null,"query":"%22mark+lee%22","tweet_volume":15082},{"name":"Morey","url":"http:\/\/twitter.com\/search?q=Morey","promoted_content":null,"query":"Morey","tweet_volume":null},{"name":"Ron Klain","url":"http:\/\/twitter.com\/search?q=%22Ron+Klain%22","promoted_content":null,"query":"%22Ron+Klain%22","tweet_volume":68409},{"name":"CMAs","url":"http:\/\/twitter.com\/search?q=CMAs","promoted_content":null,"query":"CMAs","tweet_volume":null},{"name":"Toobin","url":"http:\/\/twitter.com\/search?q=Toobin","promoted_content":null,"query":"Toobin","tweet_volume":33480},{"name":"Mormon","url":"http:\/\/twitter.com\/search?q=Mormon","promoted_content":null,"query":"Mormon","tweet_volume":null},{"name":"RIP MO3","url":"http:\/\/twitter.com\/search?q=%22RIP+MO3%22","promoted_content":null,"query":"%22RIP+MO3%22","tweet_volume":36830},{"name":"Mississippi","url":"http:\/\/twitter.com\/search?q=Mississippi","promoted_content":null,"query":"Mississippi","tweet_volume":47328},{"name":"Reba","url":"http:\/\/twitter.com\/search?q=Reba","promoted_content":null,"query":"Reba","tweet_volume":null},{"name":"Silas","url":"http:\/\/twitter.com\/search?q=Silas","promoted_content":null,"query":"Silas","tweet_volume":null},{"name":"greys anatomy","url":"http:\/\/twitter.com\/search?q=%22greys+anatomy%22","promoted_content":null,"query":"%22greys+anatomy%22","tweet_volume":11541},{"name":"shay","url":"http:\/\/twitter.com\/search?q=shay","promoted_content":null,"query":"shay","tweet_volume":17859},{"name":"Spider-Man","url":"http:\/\/twitter.com\/search?q=Spider-Man","promoted_content":null,"query":"Spider-Man","tweet_volume":40962},{"name":"Springer","url":"http:\/\/twitter.com\/search?q=Springer","promoted_content":null,"query":"Springer","tweet_volume":null},{"name":"Giannis","url":"http:\/\/twitter.com\/search?q=Giannis","promoted_content":null,"query":"Giannis","tweet_volume":null},{"name":"Kawhi","url":"http:\/\/twitter.com\/search?q=Kawhi","promoted_content":null,"query":"Kawhi","tweet_volume":null},{"name":"Freddy","url":"http:\/\/twitter.com\/search?q=Freddy","promoted_content":null,"query":"Freddy","tweet_volume":14956},{"name":"SNKRS","url":"http:\/\/twitter.com\/search?q=SNKRS","promoted_content":null,"query":"SNKRS","tweet_volume":11353},{"name":"Mavs","url":"http:\/\/twitter.com\/search?q=Mavs","promoted_content":null,"query":"Mavs","tweet_volume":null},{"name":"Harden","url":"http:\/\/twitter.com\/search?q=Harden","promoted_content":null,"query":"Harden","tweet_volume":54812},{"name":"LaVar Burton","url":"http:\/\/twitter.com\/search?q=%22LaVar+Burton%22","promoted_content":null,"query":"%22LaVar+Burton%22","tweet_volume":null},{"name":"Louis DeJoy","url":"http:\/\/twitter.com\/search?q=%22Louis+DeJoy%22","promoted_content":null,"query":"%22Louis+DeJoy%22","tweet_volume":null},{"name":"Chief of Staff","url":"http:\/\/twitter.com\/search?q=%22Chief+of+Staff%22","promoted_content":null,"query":"%22Chief+of+Staff%22","tweet_volume":142673},{"name":"Geraldo","url":"http:\/\/twitter.com\/search?q=Geraldo","promoted_content":null,"query":"Geraldo","tweet_volume":null},{"name":"EOTY","url":"http:\/\/twitter.com\/search?q=EOTY","promoted_content":null,"query":"EOTY","tweet_volume":null},{"name":"Mason McHorse","url":"http:\/\/twitter.com\/search?q=%22Mason+McHorse%22","promoted_content":null,"query":"%22Mason+McHorse%22","tweet_volume":null},{"name":"Holy Toledo","url":"http:\/\/twitter.com\/search?q=%22Holy+Toledo%22","promoted_content":null,"query":"%22Holy+Toledo%22","tweet_volume":null},{"name":"Happy Founders","url":"http:\/\/twitter.com\/search?q=%22Happy+Founders%22","promoted_content":null,"query":"%22Happy+Founders%22","tweet_volume":null},{"name":"Cy Young","url":"http:\/\/twitter.com\/search?q=%22Cy+Young%22","promoted_content":null,"query":"%22Cy+Young%22","tweet_volume":28561},{"name":"Ronald Klain","url":"http:\/\/twitter.com\/search?q=%22Ronald+Klain%22","promoted_content":null,"query":"%22Ronald+Klain%22","tweet_volume":null},{"name":"Clint Black","url":"http:\/\/twitter.com\/search?q=%22Clint+Black%22","promoted_content":null,"query":"%22Clint+Black%22","tweet_volume":null},{"name":"Shaq","url":"http:\/\/twitter.com\/search?q=Shaq","promoted_content":null,"query":"Shaq","tweet_volume":null},{"name":"austin rivers","url":"http:\/\/twitter.com\/search?q=%22austin+rivers%22","promoted_content":null,"query":"%22austin+rivers%22","tweet_volume":null},{"name":"male vocalist of the year","url":"http:\/\/twitter.com\/search?q=%22male+vocalist+of+the+year%22","promoted_content":null,"query":"%22male+vocalist+of+the+year%22","tweet_volume":null}],"as_of":"2020-11-12T05:45:24Z","created_at":"2020-11-11T12:04:16Z","locations":[{"name":"Houston","woeid":2424766}]}]